{
  "source_path": "/Users/felipecardozo/Desktop/coding/Quant Learn/Oasis/data/raw/usgs_3dep/USGS_13_n34w085_20220725.tif",
  "source_name": "USGS_13_n34w085_20220725.tif",
  "crs": "EPSG:4269",
  "bounds": [
    -85.00055555619329,
    32.99944444360705,
    -83.9994444440052,
    34.00055555579513
  ],
  "bounds_wgs84": [
    -85.00055555619329,
    32.99944444360705,
    -83.9994444440052,
    34.00055555579513
  ],
  "width": 10812,
  "height": 10812,
  "resolution": [
    9.259259269220167e-05,
    9.259259269220167e-05
  ],
  "nodata": -999999.0,
  "dtype": "float32",
  "elevation_min_m": 138.40191650390625,
  "elevation_max_m": 549.6793212890625,
  "tile_format": "Mapbox Terrain-RGB PNG",
  "encoding": "mapbox",
  "tile_size": 256,
  "minzoom": 6,
  "maxzoom": 13,
  "generated_tile_count": 933,
  "tile_coverage_by_zoom": {
    "6": 2,
    "7": 2,
    "8": 4,
    "9": 6,
    "10": 16,
    "11": 49,
    "12": 182,
    "13": 672
  },
  "public_tilejson": "/tiles/usgs_3dep/tiles.json",
  "source_registry": {
    "name": "USGS 3DEP / TNMAccess",
    "endpoint": "https://tnmaccess.nationalmap.gov/api/v1/products",
    "purpose": "Discover and download future DEM products by bbox, state, county, or area of interest.",
    "active_local_dem": "/Users/felipecardozo/Desktop/coding/Quant Learn/Oasis/data/raw/usgs_3dep/USGS_13_n34w085_20220725.tif",
    "processed_metadata": "/Users/felipecardozo/Desktop/coding/Quant Learn/Oasis/data/processed/usgs_3dep/USGS_13_n34w085_20220725.metadata.json",
    "tilejson": "/tiles/usgs_3dep/tiles.json",
    "active": true
  },
  "tnm_discovery_example": "https://tnmaccess.nationalmap.gov/api/v1/products?datasets=National+Elevation+Dataset+%28NED%29+1%2F3+arc-second&bbox=-85.000556%2C32.999444%2C-83.999444%2C34.000556&prodFormats=GeoTIFF"
}
